test/simple.v
module simple(
	input	clk,
	output	reg[7:0]sum
	);
	initial
		begin
			sum <=0; 
		end

	always@(posedge clk)begin
		sum <= sum+1;
	end
endmodule

test/simple_tb.v
`timescale 1ns/10ps
module simple_tb;
reg clk;
wire[7:0] sum;
initial
	begin
		//$dumpfile("simple.vcd");
		//$dumpvars(0, s);
		clk = 0;
		$monitor("sum = %d ",sum);
		#50 $finish;
	end

	always #5 clk = ~clk;
	simple s( clk, sum);
endmodule

test/simple.vcd
$date
	Mon Feb 27 00:16:00 2023
$end
$version
	Icarus Verilog
$end
$timescale
	10ps
$end
$scope module simple_tb $end
$scope module s $end
$var wire 1 ! clk $end
$var reg 8 " sum [7:0] $end
$upscope $end
$upscope $end
$enddefinitions $end
$comment Show the parameter values. $end
$dumpall
$end
#0
$dumpvars
b0 "
0!
$end
#500
b1 "
1!
#1000
0!
#1500
b10 "
1!
#2000
0!
#2500
b11 "
1!
#3000
0!
#3500
b100 "
1!
#4000
0!
#4500
b101 "
1!
#5000
0!
#5500
b110 "
1!
#6000
0!
#6500
b111 "
1!
#7000
0!
#7500
b1000 "
1!
#8000
0!
#8500
b1001 "
1!
#9000
0!
#9500
b1010 "
1!
#10000
0!
#10500
b1011 "
1!
#11000
0!
#11500
b1100 "
1!
#12000
0!
#12500
b1101 "
1!
#13000
0!
#13500
b1110 "
1!
#14000
0!
#14500
b1111 "
1!
#15000
0!
#15500
b10000 "
1!
#16000
0!
#16500
b10001 "
1!
#17000
0!
#17500
b10010 "
1!
#18000
0!
#18500
b10011 "
1!
#19000
0!
#19500
b10100 "
1!
#20000
0!
#20500
b10101 "
1!
#21000
0!
#21500
b10110 "
1!
#22000
0!
#22500
b10111 "
1!
#23000
0!
#23500
b11000 "
1!
#24000
0!
#24500
b11001 "
1!
#25000
0!
#25500
b11010 "
1!
#26000
0!
#26500
b11011 "
1!
#27000
0!
#27500
b11100 "
1!
#28000
0!
#28500
b11101 "
1!
#29000
0!
#29500
b11110 "
1!
#30000
0!
#30500
b11111 "
1!
#31000
0!
#31500
b100000 "
1!
#32000
0!
#32500
b100001 "
1!
#33000
0!
#33500
b100010 "
1!
#34000
0!
#34500
b100011 "
1!
#35000
0!
#35500
b100100 "
1!
#36000
0!
#36500
b100101 "
1!
#37000
0!
#37500
b100110 "
1!
#38000
0!
#38500
b100111 "
1!
#39000
0!
#39500
b101000 "
1!
#40000
0!
#40500
b101001 "
1!
#41000
0!
#41500
b101010 "
1!
#42000
0!
#42500
b101011 "
1!
#43000
0!
#43500
b101100 "
1!
#44000
0!
#44500
b101101 "
1!
#45000
0!
#45500
b101110 "
1!
#46000
0!
#46500
b101111 "
1!
#47000
0!
#47500
b110000 "
1!
#48000
0!
#48500
b110001 "
1!
#49000
0!
#49500
b110010 "
1!
#50000
0!
#50500
b110011 "
1!
#51000
0!
#51500
b110100 "
1!
#52000
0!
#52500
b110101 "
1!
#53000
0!
#53500
b110110 "
1!
#54000
0!
#54500
b110111 "
1!
#55000
0!
#55500
b111000 "
1!
#56000
0!
#56500
b111001 "
1!
#57000
0!
#57500
b111010 "
1!
#58000
0!
#58500
b111011 "
1!
#59000
0!
#59500
b111100 "
1!
#60000
0!
#60500
b111101 "
1!
#61000
0!
#61500
b111110 "
1!
#62000
0!
#62500
b111111 "
1!
#63000
0!
#63500
b1000000 "
1!
#64000
0!
#64500
b1000001 "
1!
#65000
0!
#65500
b1000010 "
1!
#66000
0!
#66500
b1000011 "
1!
#67000
0!
#67500
b1000100 "
1!
#68000
0!
#68500
b1000101 "
1!
#69000
0!
#69500
b1000110 "
1!
#70000
0!
#70500
b1000111 "
1!
#71000
0!
#71500
b1001000 "
1!
#72000
0!
#72500
b1001001 "
1!
#73000
0!
#73500
b1001010 "
1!
#74000
0!
#74500
b1001011 "
1!
#75000
0!
#75500
b1001100 "
1!
#76000
0!
#76500
b1001101 "
1!
#77000
0!
#77500
b1001110 "
1!
#78000
0!
#78500
b1001111 "
1!
#79000
0!
#79500
b1010000 "
1!
#80000
0!
#80500
b1010001 "
1!
#81000
0!
#81500
b1010010 "
1!
#82000
0!
#82500
b1010011 "
1!
#83000
0!
#83500
b1010100 "
1!
#84000
0!
#84500
b1010101 "
1!
#85000
0!
#85500
b1010110 "
1!
#86000
0!
#86500
b1010111 "
1!
#87000
0!
#87500
b1011000 "
1!
#88000
0!
#88500
b1011001 "
1!
#89000
0!
#89500
b1011010 "
1!
#90000
0!
#90500
b1011011 "
1!
#91000
0!
#91500
b1011100 "
1!
#92000
0!
#92500
b1011101 "
1!
#93000
0!
#93500
b1011110 "
1!
#94000
0!
#94500
b1011111 "
1!
#95000
0!
#95500
b1100000 "
1!
#96000
0!
#96500
b1100001 "
1!
#97000
0!
#97500
b1100010 "
1!
#98000
0!
#98500
b1100011 "
1!
#99000
0!
#99500
b1100100 "
1!
#100000
0!
#100500
b1100101 "
1!
#101000
0!
#101500
b1100110 "
1!
#102000
0!
#102500
b1100111 "
1!
#103000
0!
#103500
b1101000 "
1!
#104000
0!
#104500
b1101001 "
1!
#105000
0!
#105500
b1101010 "
1!
#106000
0!
#106500
b1101011 "
1!
#107000
0!
#107500
b1101100 "
1!
#108000
0!
#108500
b1101101 "
1!
#109000
0!
#109500
b1101110 "
1!
#110000
0!
#110500
b1101111 "
1!
#111000
0!
#111500
b1110000 "
1!
#112000
0!
#112500
b1110001 "
1!
#113000
0!
#113500
b1110010 "
1!
#114000
0!
#114500
b1110011 "
1!
#115000
0!
#115500
b1110100 "
1!
#116000
0!
#116500
b1110101 "
1!
#117000
0!
#117500
b1110110 "
1!
#118000
0!
#118500
b1110111 "
1!
#119000
0!
#119500
b1111000 "
1!
#120000
0!
#120500
b1111001 "
1!
#121000
0!
#121500
b1111010 "
1!
#122000
0!
#122500
b1111011 "
1!
#123000
0!
#123500
b1111100 "
1!
#124000
0!
#124500
b1111101 "
1!
#125000
0!
#125500
b1111110 "
1!
#126000
0!
#126500
b1111111 "
1!
#127000
0!
#127500
b10000000 "
1!
#128000
0!
#128500
b10000001 "
1!
#129000
0!
#129500
b10000010 "
1!
#130000
0!
#130500
b10000011 "
1!
#131000
0!
#131500
b10000100 "
1!
#132000
0!
#132500
b10000101 "
1!
#133000
0!
#133500
b10000110 "
1!
#134000
0!
#134500
b10000111 "
1!
#135000
0!
#135500
b10001000 "
1!
#136000
0!
#136500
b10001001 "
1!
#137000
0!
#137500
b10001010 "
1!
#138000
0!
#138500
b10001011 "
1!
#139000
0!
#139500
b10001100 "
1!
#140000
0!
#140500
b10001101 "
1!
#141000
0!
#141500
b10001110 "
1!
#142000
0!
#142500
b10001111 "
1!
#143000
0!
#143500
b10010000 "
1!
#144000
0!
#144500
b10010001 "
1!
#145000
0!
#145500
b10010010 "
1!
#146000
0!
#146500
b10010011 "
1!
#147000
0!
#147500
b10010100 "
1!
#148000
0!
#148500
b10010101 "
1!
#149000
0!
#149500
b10010110 "
1!
#150000
0!
#150500
b10010111 "
1!
#151000
0!
#151500
b10011000 "
1!
#152000
0!
#152500
b10011001 "
1!
#153000
0!
#153500
b10011010 "
1!
#154000
0!
#154500
b10011011 "
1!
#155000
0!
#155500
b10011100 "
1!
#156000
0!
#156500
b10011101 "
1!
#157000
0!
#157500
b10011110 "
1!
#158000
0!
#158500
b10011111 "
1!
#159000
0!
#159500
b10100000 "
1!
#160000
0!
#160500
b10100001 "
1!
#161000
0!
#161500
b10100010 "
1!
#162000
0!
#162500
b10100011 "
1!
#163000
0!
#163500
b10100100 "
1!
#164000
0!
#164500
b10100101 "
1!
#165000
0!
#165500
b10100110 "
1!
#166000
0!
#166500
b10100111 "
1!
#167000
0!
#167500
b10101000 "
1!
#168000
0!
#168500
b10101001 "
1!
#169000
0!
#169500
b10101010 "
1!
#170000
0!
#170500
b10101011 "
1!
#171000
0!
#171500
b10101100 "
1!
#172000
0!
#172500
b10101101 "
1!
#173000
0!
#173500
b10101110 "
1!
#174000
0!
#174500
b10101111 "
1!
#175000
0!
#175500
b10110000 "
1!
#176000
0!
#176500
b10110001 "
1!
#177000
0!
#177500
b10110010 "
1!
#178000
0!
#178500
b10110011 "
1!
#179000
0!
#179500
b10110100 "
1!
#180000
0!
#180500
b10110101 "
1!
#181000
0!
#181500
b10110110 "
1!
#182000
0!
#182500
b10110111 "
1!
#183000
0!
#183500
b10111000 "
1!
#184000
0!
#184500
b10111001 "
1!
#185000
0!
#185500
b10111010 "
1!
#186000
0!
#186500
b10111011 "
1!
#187000
0!
#187500
b10111100 "
1!
#188000
0!
#188500
b10111101 "
1!
#189000
0!
#189500
b10111110 "
1!
#190000
0!
#190500
b10111111 "
1!
#191000
0!
#191500
b11000000 "
1!
#192000
0!
#192500
b11000001 "
1!
#193000
0!
#193500
b11000010 "
1!
#194000
0!
#194500
b11000011 "
1!
#195000
0!
#195500
b11000100 "
1!
#196000
0!
#196500
b11000101 "
1!
#197000
0!
#197500
b11000110 "
1!
#198000
0!
#198500
b11000111 "
1!
#199000
0!
#199500
b11001000 "
1!
#200000
0!
#200500
b11001001 "
1!
#201000
0!
#201500
b11001010 "
1!
#202000
0!
#202500
b11001011 "
1!
#203000
0!
#203500
b11001100 "
1!
#204000
0!
#204500
b11001101 "
1!
#205000
0!
#205500
b11001110 "
1!
#206000
0!
#206500
b11001111 "
1!
#207000
0!
#207500
b11010000 "
1!
#208000
0!
#208500
b11010001 "
1!
#209000
0!
#209500
b11010010 "
1!
#210000
0!
#210500
b11010011 "
1!
#211000
0!
#211500
b11010100 "
1!
#212000
0!
#212500
b11010101 "
1!
#213000
0!
#213500
b11010110 "
1!
#214000
0!
#214500
b11010111 "
1!
#215000
0!
#215500
b11011000 "
1!
#216000
0!
#216500
b11011001 "
1!
#217000
0!
#217500
b11011010 "
1!
#218000
0!
#218500
b11011011 "
1!
#219000
0!
#219500
b11011100 "
1!
#220000
0!
#220500
b11011101 "
1!
#221000
0!
#221500
b11011110 "
1!
#222000
0!
#222500
b11011111 "
1!
#223000
0!
#223500
b11100000 "
1!
#224000
0!
#224500
b11100001 "
1!
#225000
0!
#225500
b11100010 "
1!
#226000
0!
#226500
b11100011 "
1!
#227000
0!
#227500
b11100100 "
1!
#228000
0!
#228500
b11100101 "
1!
#229000
0!
#229500
b11100110 "
1!
#230000
0!
#230500
b11100111 "
1!
#231000
0!
#231500
b11101000 "
1!
#232000
0!
#232500
b11101001 "
1!
#233000
0!
#233500
b11101010 "
1!
#234000
0!
#234500
b11101011 "
1!
#235000
0!
#235500
b11101100 "
1!
#236000
0!
#236500
b11101101 "
1!
#237000
0!
#237500
b11101110 "
1!
#238000
0!
#238500
b11101111 "
1!
#239000
0!
#239500
b11110000 "
1!
#240000
0!
#240500
b11110001 "
1!
#241000
0!
#241500
b11110010 "
1!
#242000
0!
#242500
b11110011 "
1!
#243000
0!
#243500
b11110100 "
1!
#244000
0!
#244500
b11110101 "
1!
#245000
0!
#245500
b11110110 "
1!
#246000
0!
#246500
b11110111 "
1!
#247000
0!
#247500
b11111000 "
1!
#248000
0!
#248500
b11111001 "
1!
#249000
0!
#249500
b11111010 "
1!
#250000
0!
#250500
b11111011 "
1!
#251000
0!
#251500
b11111100 "
1!
#252000
0!
#252500
b11111101 "
1!
#253000
0!
#253500
b11111110 "
1!
#254000
0!
#254500
b11111111 "
1!
#255000
0!
#255500
b0 "
1!
#256000
0!
#256500
b1 "
1!
#257000
0!
#257500
b10 "
1!
#258000
0!
#258500
b11 "
1!
#259000
0!
#259500
b100 "
1!
#260000
0!
#260500
b101 "
1!
#261000
0!
#261500
b110 "
1!
#262000
0!
#262500
b111 "
1!
#263000
0!
#263500
b1000 "
1!
#264000
0!
#264500
b1001 "
1!
#265000
0!
#265500
b1010 "
1!
#266000
0!
#266500
b1011 "
1!
#267000
0!
#267500
b1100 "
1!
#268000
0!
#268500
b1101 "
1!
#269000
0!
#269500
b1110 "
1!
#270000
0!
#270500
b1111 "
1!
#271000
0!
#271500
b10000 "
1!
#272000
0!
#272500
b10001 "
1!
#273000
0!
#273500
b10010 "
1!
#274000
0!
#274500
b10011 "
1!
#275000
0!
#275500
b10100 "
1!
#276000
0!
#276500
b10101 "
1!
#277000
0!
#277500
b10110 "
1!
#278000
0!
#278500
b10111 "
1!
#279000
0!
#279500
b11000 "
1!
#280000
0!
#280500
b11001 "
1!
#281000
0!
#281500
b11010 "
1!
#282000
0!
#282500
b11011 "
1!
#283000
0!
#283500
b11100 "
1!
#284000
0!
#284500
b11101 "
1!
#285000
0!
#285500
b11110 "
1!
#286000
0!
#286500
b11111 "
1!
#287000
0!
#287500
b100000 "
1!
#288000
0!
#288500
b100001 "
1!
#289000
0!
#289500
b100010 "
1!
#290000
0!
#290500
b100011 "
1!
#291000
0!
#291500
b100100 "
1!
#292000
0!
#292500
b100101 "
1!
#293000
0!
#293500
b100110 "
1!
#294000
0!
#294500
b100111 "
1!
#295000
0!
#295500
b101000 "
1!
#296000
0!
#296500
b101001 "
1!
#297000
0!
#297500
b101010 "
1!
#298000
0!
#298500
b101011 "
1!
#299000
0!
#299500
b101100 "
1!
#300000
0!
#300500
b101101 "
1!
#301000
0!
#301500
b101110 "
1!
#302000
0!
#302500
b101111 "
1!
#303000
0!
#303500
b110000 "
1!
#304000
0!
#304500
b110001 "
1!
#305000
0!
#305500
b110010 "
1!
#306000
0!
#306500
b110011 "
1!
#307000
0!
#307500
b110100 "
1!
#308000
0!
#308500
b110101 "
1!
#309000
0!
#309500
b110110 "
1!
#310000
0!
#310500
b110111 "
1!
#311000
0!
#311500
b111000 "
1!
#312000
0!
#312500
b111001 "
1!
#313000
0!
#313500
b111010 "
1!
#314000
0!
#314500
b111011 "
1!
#315000
0!
#315500
b111100 "
1!
#316000
0!
#316500
b111101 "
1!
#317000
0!
#317500
b111110 "
1!
#318000
0!
#318500
b111111 "
1!
#319000
0!
#319500
b1000000 "
1!
#320000
0!
#320500
b1000001 "
1!
#321000
0!
#321500
b1000010 "
1!
#322000
0!
#322500
b1000011 "
1!
#323000
0!
#323500
b1000100 "
1!
#324000
0!
#324500
b1000101 "
1!
#325000
0!
#325500
b1000110 "
1!
#326000
0!
#326500
b1000111 "
1!
#327000
0!
#327500
b1001000 "
1!
#328000
0!
#328500
b1001001 "
1!
#329000
0!
#329500
b1001010 "
1!
#330000
0!
#330500
b1001011 "
1!
#331000
0!
#331500
b1001100 "
1!
#332000
0!
#332500
b1001101 "
1!
#333000
0!
#333500
b1001110 "
1!
#334000
0!
#334500
b1001111 "
1!
#335000
0!
#335500
b1010000 "
1!
#336000
0!
#336500
b1010001 "
1!
#337000
0!
#337500
b1010010 "
1!
#338000
0!
#338500
b1010011 "
1!
#339000
0!
#339500
b1010100 "
1!
#340000
0!
#340500
b1010101 "
1!
#341000
0!
#341500
b1010110 "
1!
#342000
0!
#342500
b1010111 "
1!
#343000
0!
#343500
b1011000 "
1!
#344000
0!
#344500
b1011001 "
1!
#345000
0!
#345500
b1011010 "
1!
#346000
0!
#346500
b1011011 "
1!
#347000
0!
#347500
b1011100 "
1!
#348000
0!
#348500
b1011101 "
1!
#349000
0!
#349500
b1011110 "
1!
#350000
0!
#350500
b1011111 "
1!
#351000
0!
#351500
b1100000 "
1!
#352000
0!
#352500
b1100001 "
1!
#353000
0!
#353500
b1100010 "
1!
#354000
0!
#354500
b1100011 "
1!
#355000
0!
#355500
b1100100 "
1!
#356000
0!
#356500
b1100101 "
1!
#357000
0!
#357500
b1100110 "
1!
#358000
0!
#358500
b1100111 "
1!
#359000
0!
#359500
b1101000 "
1!
#360000
0!
#360500
b1101001 "
1!
#361000
0!
#361500
b1101010 "
1!
#362000
0!
#362500
b1101011 "
1!
#363000
0!
#363500
b1101100 "
1!
#364000
0!
#364500
b1101101 "
1!
#365000
0!
#365500
b1101110 "
1!
#366000
0!
#366500
b1101111 "
1!
#367000
0!
#367500
b1110000 "
1!
#368000
0!
#368500
b1110001 "
1!
#369000
0!
#369500
b1110010 "
1!
#370000
0!
#370500
b1110011 "
1!
#371000
0!
#371500
b1110100 "
1!
#372000
0!
#372500
b1110101 "
1!
#373000
0!
#373500
b1110110 "
1!
#374000
0!
#374500
b1110111 "
1!
#375000
0!
#375500
b1111000 "
1!
#376000
0!
#376500
b1111001 "
1!
#377000
0!
#377500
b1111010 "
1!
#378000
0!
#378500
b1111011 "
1!
#379000
0!
#379500
b1111100 "
1!
#380000
0!
#380500
b1111101 "
1!
#381000
0!
#381500
b1111110 "
1!
#382000
0!
#382500
b1111111 "
1!
#383000
0!
#383500
b10000000 "
1!
#384000
0!
#384500
b10000001 "
1!
#385000
0!
#385500
b10000010 "
1!
#386000
0!
#386500
b10000011 "
1!
#387000
0!
#387500
b10000100 "
1!
#388000
0!
#388500
b10000101 "
1!
#389000
0!
#389500
b10000110 "
1!
#390000
0!
#390500
b10000111 "
1!
#391000
0!
#391500
b10001000 "
1!
#392000
0!
#392500
b10001001 "
1!
#393000
0!
#393500
b10001010 "
1!
#394000
0!
#394500
b10001011 "
1!
#395000
0!
#395500
b10001100 "
1!
#396000
0!
#396500
b10001101 "
1!
#397000
0!
#397500
b10001110 "
1!
#398000
0!
#398500
b10001111 "
1!
#399000
0!
#399500
b10010000 "
1!
#400000
0!
#400500
b10010001 "
1!
#401000
0!
#401500
b10010010 "
1!
#402000
0!
#402500
b10010011 "
1!
#403000
0!
#403500
b10010100 "
1!
#404000
0!
#404500
b10010101 "
1!
#405000
0!
#405500
b10010110 "
1!
#406000
0!
#406500
b10010111 "
1!
#407000
0!
#407500
b10011000 "
1!
#408000
0!
#408500
b10011001 "
1!
#409000
0!
#409500
b10011010 "
1!
#410000
0!
#410500
b10011011 "
1!
#411000
0!
#411500
b10011100 "
1!
#412000
0!
#412500
b10011101 "
1!
#413000
0!
#413500
b10011110 "
1!
#414000
0!
#414500
b10011111 "
1!
#415000
0!
#415500
b10100000 "
1!
#416000
0!
#416500
b10100001 "
1!
#417000
0!
#417500
b10100010 "
1!
#418000
0!
#418500
b10100011 "
1!
#419000
0!
#419500
b10100100 "
1!
#420000
0!
#420500
b10100101 "
1!
#421000
0!
#421500
b10100110 "
1!
#422000
0!
#422500
b10100111 "
1!
#423000
0!
#423500
b10101000 "
1!
#424000
0!
#424500
b10101001 "
1!
#425000
0!
#425500
b10101010 "
1!
#426000
0!
#426500
b10101011 "
1!
#427000
0!
#427500
b10101100 "
1!
#428000
0!
#428500
b10101101 "
1!
#429000
0!
#429500
b10101110 "
1!
#430000
0!
#430500
b10101111 "
1!
#431000
0!
#431500
b10110000 "
1!
#432000
0!
#432500
b10110001 "
1!
#433000
0!
#433500
b10110010 "
1!
#434000
0!
#434500
b10110011 "
1!
#435000
0!
#435500
b10110100 "
1!
#436000
0!
#436500
b10110101 "
1!
#437000
0!
#437500
b10110110 "
1!
#438000
0!
#438500
b10110111 "
1!
#439000
0!
#439500
b10111000 "
1!
#440000
0!
#440500
b10111001 "
1!
#441000
0!
#441500
b10111010 "
1!
#442000
0!
#442500
b10111011 "
1!
#443000
0!
#443500
b10111100 "
1!
#444000
0!
#444500
b10111101 "
1!
#445000
0!
#445500
b10111110 "
1!
#446000
0!
#446500
b10111111 "
1!
#447000
0!
#447500
b11000000 "
1!
#448000
0!
#448500
b11000001 "
1!
#449000
0!
#449500
b11000010 "
1!
#450000
0!
#450500
b11000011 "
1!
#451000
0!
#451500
b11000100 "
1!
#452000
0!
#452500
b11000101 "
1!
#453000
0!
#453500
b11000110 "
1!
#454000
0!
#454500
b11000111 "
1!
#455000
0!
#455500
b11001000 "
1!
#456000
0!
#456500
b11001001 "
1!
#457000
0!
#457500
b11001010 "
1!
#458000
0!
#458500
b11001011 "
1!
#459000
0!
#459500
b11001100 "
1!
#460000
0!
#460500
b11001101 "
1!
#461000
0!
#461500
b11001110 "
1!
#462000
0!
#462500
b11001111 "
1!
#463000
0!
#463500
b11010000 "
1!
#464000
0!
#464500
b11010001 "
1!
#465000
0!
#465500
b11010010 "
1!
#466000
0!
#466500
b11010011 "
1!
#467000
0!
#467500
b11010100 "
1!
#468000
0!
#468500
b11010101 "
1!
#469000
0!
#469500
b11010110 "
1!
#470000
0!
#470500
b11010111 "
1!
#471000
0!
#471500
b11011000 "
1!
#472000
0!
#472500
b11011001 "
1!
#473000
0!
#473500
b11011010 "
1!
#474000
0!
#474500
b11011011 "
1!
#475000
0!
#475500
b11011100 "
1!
#476000
0!
#476500
b11011101 "
1!
#477000
0!
#477500
b11011110 "
1!
#478000
0!
#478500
b11011111 "
1!
#479000
0!
#479500
b11100000 "
1!
#480000
0!
#480500
b11100001 "
1!
#481000
0!
#481500
b11100010 "
1!
#482000
0!
#482500
b11100011 "
1!
#483000
0!
#483500
b11100100 "
1!
#484000
0!
#484500
b11100101 "
1!
#485000
0!
#485500
b11100110 "
1!
#486000
0!
#486500
b11100111 "
1!
#487000
0!
#487500
b11101000 "
1!
#488000
0!
#488500
b11101001 "
1!
#489000
0!
#489500
b11101010 "
1!
#490000
0!
#490500
b11101011 "
1!
#491000
0!
#491500
b11101100 "
1!
#492000
0!
#492500
b11101101 "
1!
#493000
0!
#493500
b11101110 "
1!
#494000
0!
#494500
b11101111 "
1!
#495000
0!
#495500
b11110000 "
1!
#496000
0!
#496500
b11110001 "
1!
#497000
0!
#497500
b11110010 "
1!
#498000
0!
#498500
b11110011 "
1!
#499000
0!
#499500
b11110100 "
1!
