期末/Mux_4to1_array.v
module Mux_4to1_array (
    out,
    sel,
    in0,
    in1,
    in2,
    in3
);
    input [1:0] sel;
    input [31:0] in0, in1, in2, in3;
    output [31:0] out;

    assign out = sel[1] ? (sel[0] ? in3 : in2) : (sel[0] ? in1 : in0);
endmodule

test/MUX.v
`timescale 1ns / 1ns
module MUX (
    ALUOut,
    HiOut,
    LoOut,
    Shifter,
    Signal,
    dataOut
);
    input [31:0] ALUOut;
    input [31:0] HiOut;
    input [31:0] LoOut;
    input [31:0] Shifter;
    input [5:0] Signal;
    output [31:0] dataOut;


    wire [31:0] temp;

    parameter AND = 6'b100100;
    parameter OR = 6'b100101;
    parameter ADD = 6'b100000;
    parameter SUB = 6'b100010;
    parameter SLT = 6'b101010;

    parameter SRL = 6'b000010;

    parameter DIVU = 6'b011011;
    parameter MFHI = 6'b010000;
    parameter MFLO = 6'b010010;

    wire alu, hi, lo, shif;

    assign alu  = Signal == AND | Signal == OR | Signal == ADD | Signal == SUB | Signal == SLT;
    assign hi   = Signal == MFHI;
    assign lo   = Signal == MFLO;
    assign shif = Signal == SRL;

    wire [1:0] select;
    assign select = alu ? 0 : (hi ? 1 : (lo ? 2 : 3));


    /*
    genvar i;
    generate
        for (i = 0; i < 32; i = i + 1) begin
            assign temp[i] = ALUOut[i] & alu | HiOut[i] & hi | LoOut[i] & lo | Shifter[i] & shif;
        end
    endgenerate
    */

    Mux_4to1_array mux_4to1_array (
        temp,
        select,
        ALUOut,
        HiOut,
        LoOut,
        Shifter
    );

    assign dataOut = temp;


endmodule

test/HiLo.v
`timescale 1ns / 1ns
module HiLo (
    clk,
    DivAns,
    HiOut,
    LoOut,
    reset
);
    input clk;
    input reset;
    input [63:0] DivAns;
    output [31:0] HiOut;
    output [31:0] LoOut;

    reg [63:0] HiLo;
    always @(posedge clk or reset) begin
        if (reset) begin
            HiLo <= 64'b0;
        end else begin
            HiLo <= DivAns;
        end
    end

    assign HiOut = HiLo[63:32];
    assign LoOut = HiLo[31:0];
endmodule

test/Shifter.v
`timescale 1ns / 1ns
module Shifter (
    dataA,
    dataB,
    Signal,
    dataOut,
    reset
);
    input reset;
    input [31:0] dataA;
    input [31:0] dataB;
    input [5:0] Signal;
    output [31:0] dataOut;


    wire [5:0][31:0] temp;

    assign temp[0] = dataA;


    genvar i, j;
    generate
        for (i = 0; i < 5; i = i + 1) begin
            for (j = 0; j + 2 ** (i) < 32; j = j + 1) begin
                assign temp[i+1][j] = temp[i][j+2**(i)] & dataB[i] | temp[i][j] & ~dataB[i];
            end
            for (j = 32 - 2 ** (i); j < 32; j = j + 1) begin
                assign temp[i+1][j] = temp[i][j] & ~dataB[i];
            end
        end
    endgenerate

    assign dataOut = temp[5];
    /*
=====================================================
上面為模擬範例，程式撰寫請遵照老師上課說明的方法來寫
=====================================================
*/

endmodule
/*
		for(i = 0 ; i < 5;i=i+1)begin
			for(j = 0 ; j+k < 32;j=j+1)begin
				assign temp[i+1][j] = temp[i][j+k];
			end
			for(j = j; j< 32;j=j+1)begin	
				assign temp[i+1][j] = temp[i][31];
			end
			k = k * 2;
		end
		*/

test/Mul.v
`timescale 1ns / 1ns
module Mul (
    firstart,
    clk,
    dataA,
    dataB,
    Signal,
    dataOut,
    reset
);
    input firstart;
    input clk;
    input reset;
    input [31:0] dataA;
    input [31:0] dataB;
    input [5:0] Signal;
    output [63:0] dataOut;
    reg [63:0] temp, mcnd;
    reg [31:0] mpr;
    wire [31:0] hi, lo;
    assign {hi, lo} = temp;





    always @(posedge firstart) begin
        temp <= 0;
        mpr  <= dataB;
        mcnd <= dataA;
    end

    always @(negedge clk) begin

        if (mpr[0]) temp = temp + mcnd;
        mcnd <= mcnd << 1;
        mpr  <= mpr >> 1;
    end

    assign dataOut = temp;


endmodule

test/FA.v
module FA (
    a,
    b,
    cin,
    cout,
    sum
);
    input a, b, cin;
    output cout, sum;

    wire cout_0, cout_1, cout_2, cout_3;
    and (cout_0, a, b);
    and (cout_1, a, cin);
    and (cout_2, b, cin);
    or (cout_3, cout_0, cout_1);
    or (cout, cout_3, cout_2);


    wire sum_0;
    xor (sum_0, a, b);
    xor (sum, sum_0, cin);
endmodule

test/Equal_array_6.v
module Equal_array_6 (
    equ,
    a,
    b
);
    input [5:0] a, b;
    output equ;

    wire [5:0] eor;

    genvar i;
    for (i = 0; i < 6; i = i + 1) begin
        xor (eor[i], a[i], b[i]);
    end

    wire [5:0] eq;

    or (eq[0], eor[0], eor[1]);
    or (eq[1], eor[2], eor[3]);
    or (eq[2], eor[4], eor[5]);
    or (eq[3], eq[0], eq[1]);
    or (eq[4], eq[2], eq[3]);
    not (equ, eq[4]);
endmodule

test/Mux_2to1_array.v
module Mux_2to1_array (
    out,
    sel,
    in0,
    in1
);
    input sel;
    input [31:0] in0, in1;
    output [31:0] out;

    assign out = sel ? in1 : in0;
endmodule

test/ALU.v
`timescale 1ns / 1ns
module ALU (
    dataA,
    dataB,
    Signal,
    dataOut,
    reset
);
    input reset;
    input [31:0] dataA;
    input [31:0] dataB;
    input [5:0] Signal;
    output [31:0] dataOut;

    //   Signal ( 6-bits)?
    //   AND  : 36
    //   OR   : 37
    //   ADD  : 32
    //   SUB  : 34
    //   SLT  : 42

    reg [31:0] temp;

    parameter AND = 6'b100100;
    parameter OR = 6'b100101;
    parameter ADD = 6'b100000;
    parameter SUB = 6'b100010;
    parameter SLT = 6'b101010;

    wire [31:0] a, b;
    wire [31:0] sum, wireand, wireor, ans;
    wire [32:0] carry;
    wire [31:0] sltsignal;
    Mux_2to1_array mux_2to1_array (
        sltsignal,
        sum[31],
        32'b0,
        32'b1
    );

    assign a = dataA;

    assign carry[0] = issub;


    wire isadd, issub, isor, isand, isslt;
    //assign isadd = (Signal == ADD);
    Equal_array_6 equal_array_6_0 (
        isadd,
        Signal,
        ADD
    );

    //assign issub = (Signal == SUB) || (Signal == SLT);
    wire isjustsub;
    Equal_array_6 equal_array_6_1 (
        isjustsub,
        Signal,
        SUB
    );
    or (issub, isjustsub, isslt);

    //assign isor  = (Signal == OR);
    Equal_array_6 equal_array_6_2 (
        isor,
        Signal,
        OR
    );

    //assign isand = (Signal == AND);
    Equal_array_6 equal_array_6_3 (
        isand,
        Signal,
        AND
    );

    //assign isslt = (Signal == SLT);
    Equal_array_6 equal_array_6_4 (
        isslt,
        Signal,
        SLT
    );

    wire [1:0] select;
    //assign select = isslt ? 3 : (isadd || issub) ? 0 : isor ? 1 : 2;
    or (select[1], isslt, isand);
    or (select[0], isslt, isor);


    genvar i;
    generate
        for (i = 0; i < 32; i = i + 1) begin
            FA fa (
                a[i],
                b[i],
                carry[i],
                carry[i+1],
                sum[i]
            );
            xor (b[i], dataB[i], issub);
            and (wireand[i], a[i], b[i]);
            or (wireor[i], a[i], b[i]);
        end
    endgenerate

    Mux_4to1_array mux_4to1_array (
        ans,
        select,
        sum,
        wireor,
        wireand,
        sltsignal
    );

    assign dataOut = ans;

endmodule

test/ALUControl.v
`timescale 1ns / 1ns
module ALUControl (
    clk,
    Signal,
    SignaltoALU,
    SignaltoSHT,
    SignaltoDIV,
    SignaltoMUX,
    mulreset
);
    input clk;
    input [5:0] Signal;
    output [5:0] SignaltoALU;
    output [5:0] SignaltoSHT;
    output [5:0] SignaltoDIV;
    output [5:0] SignaltoMUX;
    output reg mulreset;

    //   Signal ( 6-bits)?
    //   AND  : 36
    //   OR   : 37
    //   ADD  : 32
    //   SUB  : 34
    //   SRL  : 2
    //   SLT  : 42
    //   DIVU : 27


    reg [5:0] temp;
    reg [6:0] counter;


    parameter AND = 6'b100100;
    parameter OR = 6'b100101;
    parameter ADD = 6'b100000;
    parameter SUB = 6'b100010;
    parameter SLT = 6'b101010;

    parameter SRL = 6'b000010;
    parameter MULTU = 6'b011001;
    parameter MFHI = 6'b010000;
    parameter MFLO = 6'b010010;

    initial begin
        mulreset = 0;
    end

    always @(Signal) begin
        if (Signal == MULTU) begin
            counter = 0;
            mulreset <= 1;
        end

    end

    always @(posedge clk) begin
        temp = Signal;
        if (Signal == MULTU) begin
            counter = counter + 1;
            if (counter == 2) begin
                mulreset <= 0;
            end
            if (counter == 32) begin
                temp = 6'b111111;  // Open HiLo reg for Div
                counter = 0;
            end
        end
        /*
數32個clk然後開啟HiLo暫存器給除法器放值進去
*/
    end


    assign SignaltoALU = temp;
    assign SignaltoSHT = temp;
    assign SignaltoDIV = temp;
    assign SignaltoMUX = temp;


endmodule

test/TotalALU.v
`timescale 1ns / 1ns
module TotalALU (
    clk,
    dataA,
    dataB,
    Signal,
    Output,
    reset
);
    input reset;
    input clk;
    input [31:0] dataA;
    input [31:0] dataB;
    input [5:0] Signal;
    output [31:0] Output;

    //   Signal ( 6-bits)?
    //   AND  : 36
    //   OR   : 37
    //   ADD  : 32
    //   SUB  : 34
    //   SRL  : 2
    //   SLT  : 42
    //   DIVU : 27

    wire [31:0] temp;

    parameter AND = 6'b100100;
    parameter OR = 6'b100101;
    parameter ADD = 6'b100000;
    parameter SUB = 6'b100010;
    parameter SLT = 6'b101010;

    parameter SRL = 6'b000010;

    parameter DIVU = 6'b011011;
    parameter MFHI = 6'b010000;
    parameter MFLO = 6'b010010;

    wire [5:0] SignaltoALU;
    wire [5:0] SignaltoSHT;
    wire [5:0] SignaltoDIV;
    wire [5:0] SignaltoMUX;
    wire [31:0] ALUOut, HiOut, LoOut, ShifterOut;
    wire [31:0] dataOut;
    wire [63:0] DivAns;
    wire mulreset;





    ALUControl ALUControl (
        .clk(clk),
        .Signal(Signal),
        .SignaltoALU(SignaltoALU),
        .SignaltoSHT(SignaltoSHT),
        .SignaltoDIV(SignaltoDIV),
        .SignaltoMUX(SignaltoMUX),
        .mulreset(mulreset)
    );
    ALU ALU (
        .dataA  (dataA),
        .dataB  (dataB),
        .Signal (SignaltoALU),
        .dataOut(ALUOut),
        .reset  (reset)
    );
    /*
    Divider Divider (
        .clk(clk),
        .dataA(dataA),
        .dataB(dataB),
        .Signal(SignaltoDIV),
        .dataOut(DivAns),
        .reset(reset)
    );
    */
    Mul mul (
        .firstart(mulreset),
        .clk(clk),
        .dataA(dataA),
        .dataB(dataB),
        .Signal(SignaltoDIV),
        .dataOut(DivAns),
        .reset(reset)
    );
    Shifter Shifter (
        .dataA  (dataA),
        .dataB  (dataB),
        .Signal (SignaltoSHT),
        .dataOut(ShifterOut),
        .reset  (reset)
    );
    HiLo HiLo (
        .clk(clk),
        .DivAns(DivAns),
        .HiOut(HiOut),
        .LoOut(LoOut),
        .reset(reset)
    );
    MUX MUX (
        .ALUOut (ALUOut),
        .HiOut  (HiOut),
        .LoOut  (LoOut),
        .Shifter(ShifterOut),
        .Signal (SignaltoMUX),
        .dataOut(dataOut)
    );

    assign Output = dataOut;


endmodule

test/tb_ALU.v
`timescale 1ns / 1ns
module tb_ALU ();
    reg clk, rst;
    reg [5:0] ctrl;
    reg [31:0] inputA, inputB, ans;
    wire [31:0] out;
    integer fp_r, fp_r_ans, eof, e;


    initial begin
        clk = 1'b1;
        forever #5 clk = ~clk;
    end

    initial begin
        inputA <= 0;
        inputB <= 0;
        ctrl   <= 0;
        $dumpfile("test.vcd");
        $dumpvars(2, alu);
        eof = 0;
        rst = 1'b1;
        #10;
        rst = 1'b0;
        fp_r = $fopen("input.txt", "r");

        fp_r_ans = $fopen("ans.txt", "r");
        $display("Start\n");
        eof = $fscanf(fp_r_ans, "%d", ans);
        while (eof != -1) begin
            e = $fscanf(fp_r, "%d%d%d", ctrl, inputA, inputB);
            $write("%d: Input: ", $time / 10);
            if (ctrl == 6'd36) $write("AND(%d)", ctrl);
            else if (ctrl == 6'd37) $write("OR(%d) ", ctrl);
            else if (ctrl == 6'd32) $write("ADD(%d) ", ctrl);
            else if (ctrl == 6'd34) $write("SUB(%d) ", ctrl);
            else if (ctrl == 6'd42) $write("SLT(%d) ", ctrl);
            else if (ctrl == 6'd2) $write("SRL(%d) ", ctrl);
            else if (ctrl == 6'd27) $write("DIVU(%d) ", ctrl);
            else if (ctrl == 6'd25) $write("MULTU(%d) ", ctrl);
            $display("%d%d", inputA, inputB);
            if (ctrl == 32'd25) begin
                #330;
                $display("%d: MUL End\n", $time / 10);
                #10;
                #10;

                $display("                   Move Hi");
                ctrl = 6'd16;
                #10;
                if (ans == out)
                    $display(
                        "%d: Correct: Your answer is:%d,\n                                 Correct answer is:%d\n",
                        $time / 10,
                        out,
                        ans
                    );
                else
                    $display(
                        "%d: Wrong Answer: Your answer is:%d,\n                                             Correct answer is:%d\n",
                        $time / 10,
                        out,
                        ans
                    );
                $display("                   Move Lo");
                ctrl = 6'd18;
                eof  = $fscanf(fp_r_ans, "%d", ans);
                #10;
                if (ans == out)
                    $display(
                        "%d: Correct: Your answer is:%d,\n                                 Correct answer is:%d\n",
                        $time / 10,
                        out,
                        ans
                    );
                else
                    $display(
                        "%d: Wrong Answer: Your answer is:%d,\n                                             Correct answer is:%d\n",
                        $time / 10,
                        out,
                        ans
                    );
            end else begin
                #10;
                if (ans == out)
                    $display(
                        "%d: Correct: Your answer is:%d,\n                                 Correct answer is:%d\n",
                        $time / 10,
                        out,
                        ans
                    );
                else
                    $display(
                        "%d: Wrong Answer: Your answer is:%d,\n                                             Correct answer is:%d\n",
                        $time / 10,
                        out,
                        ans
                    );
            end
            eof = $fscanf(fp_r_ans, "%d", ans);
        end
        $fclose(fp_r);
        $fclose(fp_r_ans);
        $display("Simulation End\n");
        $finish;
        $stop();
    end

    TotalALU alu (
        .clk(clk),
        .reset(rst),
        .dataA(inputA),
        .dataB(inputB),
        .Signal(ctrl),
        .Output(out)
    );

endmodule

/*
	AND  : 36
	OR   : 37
	ADD  : 32
	SUB  : 34
	SLT  : 42
	SRL  : 02
	DIVU : 27
*/

test/test.vcd
$date
	Tue May 02 23:24:59 2023
$end
$version
	Icarus Verilog
$end
$timescale
	1ns
$end
$scope module tb_ALU $end
$scope module alu $end
$var wire 32 ! Output [31:0] $end
$var wire 6 " Signal [5:0] $end
$var wire 1 # clk $end
$var wire 32 $ dataA [31:0] $end
$var wire 32 % dataB [31:0] $end
$var wire 1 & reset $end
$var wire 1 ' mulreset $end
$var wire 32 ( dataOut [31:0] $end
$var wire 6 ) SignaltoSHT [5:0] $end
$var wire 6 * SignaltoMUX [5:0] $end
$var wire 6 + SignaltoDIV [5:0] $end
$var wire 6 , SignaltoALU [5:0] $end
$var wire 32 - ShifterOut [31:0] $end
$var wire 32 . LoOut [31:0] $end
$var wire 32 / HiOut [31:0] $end
$var wire 64 0 DivAns [63:0] $end
$var wire 32 1 ALUOut [31:0] $end
$var parameter 6 2 ADD $end
$var parameter 6 3 AND $end
$var parameter 6 4 DIVU $end
$var parameter 6 5 MFHI $end
$var parameter 6 6 MFLO $end
$var parameter 6 7 OR $end
$var parameter 6 8 SLT $end
$var parameter 6 9 SRL $end
$var parameter 6 : SUB $end
$scope module ALU $end
$var wire 32 ; a [31:0] $end
$var wire 32 < dataA [31:0] $end
$var wire 32 = dataB [31:0] $end
$var wire 32 > dataOut [31:0] $end
$var wire 1 ? issub $end
$var wire 1 & reset $end
$var wire 32 @ wireor [31:0] $end
$var wire 32 A wireand [31:0] $end
$var wire 32 B sum [31:0] $end
$var wire 32 C sltsignal [31:0] $end
$var wire 2 D select [1:0] $end
$var wire 1 E isslt $end
$var wire 1 F isor $end
$var wire 1 G isjustsub $end
$var wire 1 H isand $end
$var wire 1 I isadd $end
$var wire 33 J carry [32:0] $end
$var wire 32 K b [31:0] $end
$var wire 32 L ans [31:0] $end
$var wire 6 M Signal [5:0] $end
$var parameter 6 N ADD $end
$var parameter 6 O AND $end
$var parameter 6 P OR $end
$var parameter 6 Q SLT $end
$var parameter 6 R SUB $end
$upscope $end
$scope module ALUControl $end
$var wire 6 S Signal [5:0] $end
$var wire 6 T SignaltoALU [5:0] $end
$var wire 6 U SignaltoDIV [5:0] $end
$var wire 6 V SignaltoMUX [5:0] $end
$var wire 6 W SignaltoSHT [5:0] $end
$var wire 1 # clk $end
$var parameter 6 X ADD $end
$var parameter 6 Y AND $end
$var parameter 6 Z MFHI $end
$var parameter 6 [ MFLO $end
$var parameter 6 \ MULTU $end
$var parameter 6 ] OR $end
$var parameter 6 ^ SLT $end
$var parameter 6 _ SRL $end
$var parameter 6 ` SUB $end
$var reg 7 a counter [6:0] $end
$var reg 1 ' mulreset $end
$var reg 6 b temp [5:0] $end
$upscope $end
$scope module HiLo $end
$var wire 1 # clk $end
$var wire 1 & reset $end
$var wire 32 c LoOut [31:0] $end
$var wire 32 d HiOut [31:0] $end
$var wire 64 e DivAns [63:0] $end
$var reg 64 f HiLo [63:0] $end
$upscope $end
$scope module MUX $end
$var wire 32 g ALUOut [31:0] $end
$var wire 32 h HiOut [31:0] $end
$var wire 32 i LoOut [31:0] $end
$var wire 6 j Signal [5:0] $end
$var wire 1 k alu $end
$var wire 32 l dataOut [31:0] $end
$var wire 32 m temp [31:0] $end
$var wire 1 n shif $end
$var wire 2 o select [1:0] $end
$var wire 1 p lo $end
$var wire 1 q hi $end
$var wire 32 r Shifter [31:0] $end
$var parameter 6 s ADD $end
$var parameter 6 t AND $end
$var parameter 6 u DIVU $end
$var parameter 6 v MFHI $end
$var parameter 6 w MFLO $end
$var parameter 6 x OR $end
$var parameter 6 y SLT $end
$var parameter 6 z SRL $end
$var parameter 6 { SUB $end
$upscope $end
$scope module Shifter $end
$var wire 6 | Signal [5:0] $end
$var wire 32 } dataA [31:0] $end
$var wire 32 ~ dataB [31:0] $end
$var wire 1 & reset $end
$var wire 192 !" temp [191:0] $end
$var wire 32 "" dataOut [31:0] $end
$upscope $end
$scope module mul $end
$var wire 6 #" Signal [5:0] $end
$var wire 1 # clk $end
$var wire 32 $" dataA [31:0] $end
$var wire 32 %" dataB [31:0] $end
$var wire 64 &" dataOut [63:0] $end
$var wire 1 ' firstart $end
$var wire 1 & reset $end
$var wire 32 '" lo [31:0] $end
$var wire 32 (" hi [31:0] $end
$var reg 64 )" mcnd [63:0] $end
$var reg 32 *" mpr [31:0] $end
$var reg 64 +" temp [63:0] $end
$upscope $end
$upscope $end
$upscope $end
$enddefinitions $end
$comment Show the parameter values. $end
$dumpall
b100010 {
b10 z
b101010 y
b100101 x
b10010 w
b10000 v
b11011 u
b100100 t
b100000 s
b100010 `
b10 _
b101010 ^
b100101 ]
b11001 \
b10010 [
b10000 Z
b100100 Y
b100000 X
b100010 R
b101010 Q
b100101 P
b100100 O
b100000 N
b100010 :
b10 9
b101010 8
b100101 7
b10010 6
b10000 5
b11011 4
b100100 3
b100000 2
$end
#0
$dumpvars
bx +"
bx *"
bx )"
bx ("
bx '"
bx &"
b0 %"
b0 $"
bx #"
b0 ""
b0 !"
b0 ~
b0 }
bx |
b0 r
xq
xp
bx o
xn
bx m
bx l
xk
bx j
b0 i
b0 h
bx g
b0 f
bx e
b0 d
b0 c
bx b
bx a
bx W
bx V
bx U
bx T
b0 S
bx M
bx L
bx K
bx J
xI
xH
xG
xF
xE
bx D
b0x C
bx B
b0 A
bx @
x?
bx >
b0 =
b0 <
b0 ;
bx 1
bx 0
b0 /
b0 .
b0 -
bx ,
bx +
bx *
bx )
bx (
0'
1&
b0 %
b0 $
1#
b0 "
bx !
$end
#5
b0xxxxxxxxxxxxxxxxxxxxxxxxxxxxxxx *"
bx0 )"
0#
#10
bx /
bx d
bx h
bx .
bx c
bx i
bx f
b0 C
b1000 !
b1000 (
b1000 l
b1000 m
b10110 B
b1000 1
b1000 >
b1000 g
b1000 L
b1010 K
b10 D
b10000 J
0?
0E
1H
0F
0G
0I
b0 o
1k
b1000 A
b1110 @
0q
0p
0n
b100100 *
b100100 V
b100100 j
b100100 +
b100100 U
b100100 #"
b100100 )
b100100 W
b100100 |
b100100 ,
b100100 M
b100100 T
b100100 b
1#
b1010 %
b1010 =
b1010 ~
b1010 %"
b1100 ;
b11000000000000000000000000000000110000000000000000000000000000110000000000000000000000000000001100 !"
b1100 $
b1100 <
b1100 }
b1100 $"
b100100 "
b100100 S
0&
#15
b0xxxxxxxxxxxxxxxxxxxxxxxxxxxxxx *"
bx00 )"
0#
#20
b1110 !
b1110 (
b1110 l
b1110 m
b1110 1
b1110 >
b1110 g
b1110 L
b1 D
0H
1F
b100101 *
b100101 V
b100101 j
b100101 +
b100101 U
b100101 #"
b100101 )
b100101 W
b100101 |
b100101 ,
b100101 M
b100101 T
b100101 b
1#
b100101 "
b100101 S
#25
b0xxxxxxxxxxxxxxxxxxxxxxxxxxxxx *"
bx000 )"
0#
#30
b10110 !
b10110 (
b10110 l
b10110 m
b10110 1
b10110 >
b10110 g
b10110 L
b0 D
0F
1I
b100000 *
b100000 V
b100000 j
b100000 +
b100000 U
b100000 #"
b100000 )
b100000 W
b100000 |
b100000 ,
b100000 M
b100000 T
b100000 b
1#
b100000 "
b100000 S
#35
b0xxxxxxxxxxxxxxxxxxxxxxxxxxxx *"
bx0000 )"
0#
#40
b0 C
b10 !
b10 (
b10 l
b10 m
b10 1
b10 >
b10 g
b10 L
b100 A
b11111111111111111111111111111101 @
b10 B
b11111111111111111111111111110101 K
b111111111111111111111111111111011 J
1?
1G
0I
b100010 *
b100010 V
b100010 j
b100010 +
b100010 U
b100010 #"
b100010 )
b100010 W
b100010 |
b100010 ,
b100010 M
b100010 T
b100010 b
1#
b100010 "
b100010 S
#45
b0xxxxxxxxxxxxxxxxxxxxxxxxxxx *"
bx00000 )"
0#
#50
b11 D
1E
0G
b0 !
b0 (
b0 l
b0 m
b0 1
b0 >
b0 g
b0 L
b1010 B
b11 -
b11 r
b11 ""
b1100 A
b11111111111111111111111111111101 K
b110000000000000000000000000000001100000000000000000000000000000011000000000000000000000000000000110000000000000000000000000000110000000000000000000000000000001100 !"
b101010 *
b101010 V
b101010 j
b101010 +
b101010 U
b101010 #"
b101010 )
b101010 W
b101010 |
b101010 ,
b101010 M
b101010 T
b101010 b
1#
b10 %
b10 =
b10 ~
b10 %"
b101010 "
b101010 S
#55
b0xxxxxxxxxxxxxxxxxxxxxxxxxx *"
bx000000 )"
0#
#60
b1 !
b1 (
b1 l
b1 m
b1 1
b1 >
b1 g
b1 L
b1 C
b11001111 J
b0 -
b0 r
b0 ""
b11111111111111111111111101110111 @
b11111111111111111111111110011100 B
b11111111111111111111111100110111 K
b100100 A
1#
b11001000 %
b11001000 =
b11001000 ~
b11001000 %"
b1100100 ;
b1100100000000000000000000000000011001000000000000000000000000000110010000000000000000000000000001100100 !"
b1100100 $
b1100100 <
b1100100 }
b1100100 $"
#65
b0xxxxxxxxxxxxxxxxxxxxxxxxx *"
bx0000000 )"
0#
#70
b0 C
b1110 1
b1110 >
b1110 g
b1110 L
b0 D
0?
0E
b11 !
b11 (
b11 l
b11 m
b11 -
b11 r
b11 ""
b11 o
b0 J
b1110 B
0k
b10 K
b0 A
b1110 @
1n
b10 *
b10 V
b10 j
b10 +
b10 U
b10 #"
b10 )
b10 W
b10 |
b10 ,
b10 M
b10 T
b10 b
1#
b10 %
b10 =
b10 ~
b10 %"
b1100 ;
b110000000000000000000000000000001100000000000000000000000000000011000000000000000000000000000000110000000000000000000000000000110000000000000000000000000000001100 !"
b1100 $
b1100 <
b1100 }
b1100 $"
b10 "
b10 S
#75
b0xxxxxxxxxxxxxxxxxxxxxxxx *"
bx00000000 )"
0#
#80
b10 !
b10 (
b10 l
b10 m
b10 -
b10 r
b10 ""
b10000110 1
b10000110 >
b10000110 g
b10000110 L
b10000110 B
b110 K
b10000110 @
1#
b110 %
b110 =
b110 ~
b110 %"
b10000000 ;
b100000000000000000000000000000001000000000000000000000000000000010000000000000000000000000001000000000000000000000000000001000000000000000000000000000000010000000 !"
b10000000 $
b10000000 <
b10000000 }
b10000000 $"
#85
b0xxxxxxxxxxxxxxxxxxxxxxx *"
bx000000000 )"
0#
#90
b1 C
b111111111111111111111111111111 !
b111111111111111111111111111111 (
b111111111111111111111111111111 l
b111111111111111111111111111111 m
b111111111111111111111111111111 -
b111111111111111111111111111111 r
b111111111111111111111111111111 ""
b10000000000000000000000000000000 1
b10000000000000000000000000000000 >
b10000000000000000000000000000000 g
b10000000000000000000000000000000 L
b11111111111111111111111111111110 J
b10000000000000000000000000000000 B
b1 K
b1 A
b1111111111111111111111111111111 @
1#
b1 %
b1 =
b1 ~
b1 %"
b1111111111111111111111111111111 ;
b1111111111111111111111111111110011111111111111111111111111111100111111111111111111111111111111001111111111111111111111111111110011111111111111111111111111111101111111111111111111111111111111 !"
b1111111111111111111111111111111 $
b1111111111111111111111111111111 <
b1111111111111111111111111111111 }
b1111111111111111111111111111111 $"
#95
b0xxxxxxxxxxxxxxxxxxxxxx *"
bx0000000000 )"
0#
#100
b11111111111111111111111111 !
b11111111111111111111111111 (
b11111111111111111111111111 l
b11111111111111111111111111 m
b10000000000000000000000000000100 1
b10000000000000000000000000000100 >
b10000000000000000000000000000100 g
b10000000000000000000000000000100 L
b11111111111111111111111111 -
b11111111111111111111111111 r
b11111111111111111111111111 ""
b10000000000000000000000000000100 B
b101 A
b101 K
b111111111111111111111111110000001111111111111111111111111100000011111111111111111111111111001111111111111111111111111111110011111111111111111111111111111101111111111111111111111111111111 !"
1#
b101 %
b101 =
b101 ~
b101 %"
#105
b0xxxxxxxxxxxxxxxxxxxxx *"
bx00000000000 )"
0#
#110
b1111111111111111111111111 !
b1111111111111111111111111 (
b1111111111111111111111111 l
b1111111111111111111111111 m
b1111111111111111111111111 -
b1111111111111111111111111 r
b1111111111111111111111111 ""
b10000000000000000000000000000101 1
b10000000000000000000000000000101 >
b10000000000000000000000000000101 g
b10000000000000000000000000000101 L
b11111111111111111111111111111100 J
b10000000000000000000000000000101 B
b110 A
b110 K
b11111111111111111111111110000000111111111111111111111111100000001111111111111111111111111000111111111111111111111111111110111111111111111111111111111111101111111111111111111111111111111 !"
1#
b110 %
b110 =
b110 ~
b110 %"
#115
b0xxxxxxxxxxxxxxxxxxxx *"
bx000000000000 )"
0#
#120
b0 ("
b0 '"
b11110 )"
b10001 *"
b0 0
b0 e
b0 &"
b0 +"
1'
b0 C
b0 !
b0 (
b0 l
b0 m
b101111 1
b101111 >
b101111 g
b101111 L
b10000 A
b100000 J
b0 -
b0 r
b0 ""
b101111 B
b10001 K
b11111 @
0n
b11001 *
b11001 V
b11001 j
b11001 +
b11001 U
b11001 #"
b11001 )
b11001 W
b11001 |
b11001 ,
b11001 M
b11001 T
b11001 b
b1 a
1#
b10001 %
b10001 =
b10001 ~
b10001 %"
b11110 ;
b111100000000000000000000000000001111000000000000000000000000000011110000000000000000000000000000111100000000000000000000000000011110 !"
b11110 $
b11110 <
b11110 }
b11110 $"
b11001 "
b11001 S
#125
b1000 *"
b111100 )"
b11110 '"
b11110 0
b11110 e
b11110 &"
b11110 +"
0#
#130
b0 /
b0 d
b0 h
b11110 .
b11110 c
b11110 i
0'
b11110 f
b10 a
1#
#135
b100 *"
b1111000 )"
0#
#140
b11 a
1#
#145
b10 *"
b11110000 )"
0#
#150
b100 a
1#
#155
b1 *"
b111100000 )"
0#
#160
b101 a
1#
#165
b0 *"
b1111000000 )"
b111111110 '"
b111111110 0
b111111110 e
b111111110 &"
b111111110 +"
0#
#170
b111111110 .
b111111110 c
b111111110 i
b111111110 f
b110 a
1#
#175
b11110000000 )"
0#
#180
b111 a
1#
#185
b111100000000 )"
0#
#190
b1000 a
1#
#195
b1111000000000 )"
0#
#200
b1001 a
1#
#205
b11110000000000 )"
0#
#210
b1010 a
1#
#215
b111100000000000 )"
0#
#220
b1011 a
1#
#225
b1111000000000000 )"
0#
#230
b1100 a
1#
#235
b11110000000000000 )"
0#
#240
b1101 a
1#
#245
b111100000000000000 )"
0#
#250
b1110 a
1#
#255
b1111000000000000000 )"
0#
#260
b1111 a
1#
#265
b11110000000000000000 )"
0#
#270
b10000 a
1#
#275
b111100000000000000000 )"
0#
#280
b10001 a
1#
#285
b1111000000000000000000 )"
0#
#290
b10010 a
1#
#295
b11110000000000000000000 )"
0#
#300
b10011 a
1#
#305
b111100000000000000000000 )"
0#
#310
b10100 a
1#
#315
b1111000000000000000000000 )"
0#
#320
b10101 a
1#
#325
b11110000000000000000000000 )"
0#
#330
b10110 a
1#
#335
b111100000000000000000000000 )"
0#
#340
b10111 a
1#
#345
b1111000000000000000000000000 )"
0#
#350
b11000 a
1#
#355
b11110000000000000000000000000 )"
0#
#360
b11001 a
1#
#365
b111100000000000000000000000000 )"
0#
#370
b11010 a
1#
#375
b1111000000000000000000000000000 )"
0#
#380
b11011 a
1#
#385
b11110000000000000000000000000000 )"
0#
#390
b11100 a
1#
#395
b111100000000000000000000000000000 )"
0#
#400
b11101 a
1#
#405
b1111000000000000000000000000000000 )"
0#
#410
b11110 a
1#
#415
b11110000000000000000000000000000000 )"
0#
#420
b11111 a
1#
#425
b111100000000000000000000000000000000 )"
0#
#430
b111111 *
b111111 V
b111111 j
b111111 +
b111111 U
b111111 #"
b111111 )
b111111 W
b111111 |
b111111 ,
b111111 M
b111111 T
b111111 b
b0 a
1#
#435
b1111000000000000000000000000000000000 )"
0#
#440
b1 a
b11001 *
b11001 V
b11001 j
b11001 +
b11001 U
b11001 #"
b11001 )
b11001 W
b11001 |
b11001 ,
b11001 M
b11001 T
b11001 b
1#
#445
b11110000000000000000000000000000000000 )"
0#
#450
b10 a
1#
#455
b111100000000000000000000000000000000000 )"
0#
#460
b11 a
1#
#465
b1111000000000000000000000000000000000000 )"
0#
#470
b1 o
1q
b10000 *
b10000 V
b10000 j
b10000 +
b10000 U
b10000 #"
b10000 )
b10000 W
b10000 |
b10000 ,
b10000 M
b10000 T
b10000 b
1#
b10000 "
b10000 S
#475
b11110000000000000000000000000000000000000 )"
0#
