test/MUX.v
`timescale 1ns / 1ns
module MUX (
    ALUOut,
    HiOut,
    LoOut,
    Shifter,
    Signal,
    dataOut
);
    input [31:0] ALUOut;
    input [31:0] HiOut;
    input [31:0] LoOut;
    input [31:0] Shifter;
    input [5:0] Signal;
    output [31:0] dataOut;


    wire [31:0] temp;

    parameter AND = 6'b100100;
    parameter OR = 6'b100101;
    parameter ADD = 6'b100000;
    parameter SUB = 6'b100010;
    parameter SLT = 6'b101010;

    parameter SRL = 6'b000010;

    parameter DIVU = 6'b011011;
    parameter MFHI = 6'b010000;
    parameter MFLO = 6'b010010;

    wire alu, hi, lo, shif;

    assign alu  = Signal == AND | Signal == OR | Signal == ADD | Signal == SUB | Signal == SLT;
    assign hi   = Signal == MFHI;
    assign lo   = Signal == MFLO;
    assign shif = Signal == SRL;

    genvar i;
    generate
        for (i = 0; i < 32; i = i + 1) begin
            assign temp[i] = ALUOut[i] & alu | HiOut[i] & hi | LoOut[i] & lo | Shifter[i] & shif;
        end
    endgenerate


    assign dataOut = temp;
    /*
=====================================================
上面為模擬範例，程式撰寫請遵照老師上課說明的方法來寫
=====================================================
*/

endmodule

test/HiLo.v
`timescale 1ns / 1ns
module HiLo (
    clk,
    DivAns,
    HiOut,
    LoOut,
    reset
);
    input clk;
    input reset;
    input [63:0] DivAns;
    output [31:0] HiOut;
    output [31:0] LoOut;

    reg [63:0] HiLo;
    always @(posedge clk or reset) begin
        if (reset) begin
            HiLo <= 64'b0;
        end else begin
            HiLo <= DivAns;
        end
    end

    assign HiOut = HiLo[63:32];
    assign LoOut = HiLo[31:0];
endmodule

期末/Mux_2to1.v
module Mux_2to1 (
    out,
    sel,
    in0,
    in1
);
    input sel;
    input in0, in1;
    output out;

    assign out = sel ? in1 : in0;
endmodule

test/Shifter.v
`timescale 1ns / 1ns
module Shifter (
    dataA,
    dataB,
    Signal,
    dataOut,
    reset
);
    input reset;
    input [31:0] dataA;
    input [31:0] dataB;
    input [5:0] Signal;
    output [31:0] dataOut;


    wire [5:0][31:0] temp;

    assign temp[0] = dataA;


    genvar i, j;
    generate
        for (i = 0; i < 5; i = i + 1) begin
            for (j = 0; j + 2 ** (i) < 32; j = j + 1) begin
                //assign temp[i+1][j] = temp[i][j+2**(i)] & dataB[i] | temp[i][j] & ~dataB[i];
                Mux_2to1 mux2to1 (
                    temp[i+1][j],
                    dataB[i],
                    temp[i][j],
                    temp[i][j+2**(i)]
                );
            end
            for (j = 32 - 2 ** (i); j < 32; j = j + 1) begin
                //assign temp[i+1][j] = temp[i][j] & ~dataB[i];
                Mux_2to1 mux2to1 (
                    temp[i+1][j],
                    dataB[i],
                    temp[i][j],
                    1'b0
                );
            end
        end
    endgenerate

    assign dataOut = temp[5];


endmodule

test/Mul.v
`timescale 1ns / 1ns
module Mul (
    firstart,
    clk,
    dataA,
    dataB,
    Signal,
    dataOut,
    reset
);
    input firstart;
    input clk;
    input reset;
    input [31:0] dataA;
    input [31:0] dataB;
    input [5:0] Signal;
    output [63:0] dataOut;
    reg [63:0] temp, mcnd;
    reg [31:0] mpr;
    wire [31:0] hi, lo;
    assign {hi, lo} = temp;





    always @(posedge firstart) begin
        temp <= 0;
        mpr  <= dataB;
        mcnd <= dataA;
    end

    always @(negedge clk) begin

        if (mpr[0]) temp = temp + mcnd;
        mcnd <= mcnd << 1;
        mpr  <= mpr >> 1;
    end

    assign dataOut = temp;


endmodule

期末/Mux_4to1_array.v
module Mux_4to1_array (
    out,
    sel,
    in0,
    in1,
    in2,
    in3
);
    input [1:0] sel;
    input [31:0] in0, in1, in2, in3;
    output [31:0] out;

    assign out = sel[1] ? (sel[0] ? in3 : in2) : (sel[0] ? in1 : in0);
endmodule

test/FA.v
module FA (
    a,
    b,
    cin,
    cout,
    sum
);
    input a, b, cin;
    output cout, sum;

    wire cout_0, cout_1, cout_2, cout_3;
    and (cout_0, a, b);
    and (cout_1, a, cin);
    and (cout_2, b, cin);
    or (cout_3, cout_0, cout_1);
    or (cout, cout_3, cout_2);


    wire sum_0;
    xor (sum_0, a, b);
    xor (sum, sum_0, cin);
endmodule

test/Mux_2to1_array.v
module Mux_2to1_array (
    out,
    sel,
    in0,
    in1
);
    input sel;
    input [31:0] in0, in1;
    output [31:0] out;

    assign out = sel ? in1 : in0;
endmodule

test/ALU.v
`timescale 1ns / 1ns
module ALU (
    dataA,
    dataB,
    Signal,
    dataOut,
    reset
);
    input reset;
    input [31:0] dataA;
    input [31:0] dataB;
    input [5:0] Signal;
    output [31:0] dataOut;

    //   Signal ( 6-bits)?
    //   AND  : 36
    //   OR   : 37
    //   ADD  : 32
    //   SUB  : 34
    //   SLT  : 42

    reg [31:0] temp;

    parameter AND = 6'b100100;
    parameter OR = 6'b100101;
    parameter ADD = 6'b100000;
    parameter SUB = 6'b100010;
    parameter SLT = 6'b101010;

    wire [31:0] a, b;
    wire [31:0] sum, wireand, wireor, ans;
    wire [32:0] carry;
    wire [31:0] sltsignal;
    Mux_2to1_array mux_2to1_array (
        sltsignal,
        sum[31],
        32'b0,
        32'b1
    );

    assign a = dataA;

    assign carry[0] = issub;


    wire isadd, issub, isor, isand, isslt;
    assign isadd = (Signal == ADD);
    assign issub = (Signal == SUB) || (Signal == SLT);
    assign isor  = (Signal == OR);
    assign isand = (Signal == AND);
    assign isslt = (Signal == SLT);

    wire [1:0] select;
    assign select = isslt ? 3 : (isadd || issub) ? 0 : isor ? 1 : 2;

    genvar i;
    generate
        for (i = 0; i < 32; i = i + 1) begin
            FA fa (
                a[i],
                b[i],
                carry[i],
                carry[i+1],
                sum[i]
            );
            xor (b[i], dataB[i], issub);
            and (wireand[i], a[i], b[i]);
            or (wireor[i], a[i], b[i]);
        end
    endgenerate

    Mux_4to1_array mux_4to1_array (
        ans,
        select,
        sum,
        wireor,
        wireand,
        sltsignal
    );

    assign dataOut = ans;

endmodule

test/ALUControl.v
`timescale 1ns / 1ns
module ALUControl (
    clk,
    Signal,
    SignaltoALU,
    SignaltoSHT,
    SignaltoDIV,
    SignaltoMUX,
    mulreset
);
    input clk;
    input [5:0] Signal;
    output [5:0] SignaltoALU;
    output [5:0] SignaltoSHT;
    output [5:0] SignaltoDIV;
    output [5:0] SignaltoMUX;
    output reg mulreset;

    //   Signal ( 6-bits)?
    //   AND  : 36
    //   OR   : 37
    //   ADD  : 32
    //   SUB  : 34
    //   SRL  : 2
    //   SLT  : 42
    //   DIVU : 27


    reg [5:0] temp;
    reg [6:0] counter;


    parameter AND = 6'b100100;
    parameter OR = 6'b100101;
    parameter ADD = 6'b100000;
    parameter SUB = 6'b100010;
    parameter SLT = 6'b101010;

    parameter SRL = 6'b000010;
    parameter MULTU = 6'b011001;
    parameter MFHI = 6'b010000;
    parameter MFLO = 6'b010010;

    initial begin
        mulreset = 0;
    end

    always @(Signal) begin
        if (Signal == MULTU) begin
            counter = 0;
            mulreset <= 1;
        end

    end

    always @(posedge clk) begin
        temp = Signal;
        if (Signal == MULTU) begin
            counter = counter + 1;
            if (counter == 2) begin
                mulreset <= 0;
            end
            if (counter == 32) begin
                temp = 6'b111111;  // Open HiLo reg for Div
                counter = 0;
            end
        end
        /*
數32個clk然後開啟HiLo暫存器給除法器放值進去
*/
    end


    assign SignaltoALU = temp;
    assign SignaltoSHT = temp;
    assign SignaltoDIV = temp;
    assign SignaltoMUX = temp;


endmodule

test/TotalALU.v
`timescale 1ns / 1ns
module TotalALU (
    clk,
    dataA,
    dataB,
    Signal,
    Output,
    reset
);
    input reset;
    input clk;
    input [31:0] dataA;
    input [31:0] dataB;
    input [5:0] Signal;
    output [31:0] Output;

    //   Signal ( 6-bits)?
    //   AND  : 36
    //   OR   : 37
    //   ADD  : 32
    //   SUB  : 34
    //   SRL  : 2
    //   SLT  : 42
    //   DIVU : 27

    wire [31:0] temp;

    parameter AND = 6'b100100;
    parameter OR = 6'b100101;
    parameter ADD = 6'b100000;
    parameter SUB = 6'b100010;
    parameter SLT = 6'b101010;

    parameter SRL = 6'b000010;

    parameter DIVU = 6'b011011;
    parameter MFHI = 6'b010000;
    parameter MFLO = 6'b010010;

    wire [5:0] SignaltoALU;
    wire [5:0] SignaltoSHT;
    wire [5:0] SignaltoDIV;
    wire [5:0] SignaltoMUX;
    wire [31:0] ALUOut, HiOut, LoOut, ShifterOut;
    wire [31:0] dataOut;
    wire [63:0] DivAns;
    wire mulreset;





    ALUControl ALUControl (
        .clk(clk),
        .Signal(Signal),
        .SignaltoALU(SignaltoALU),
        .SignaltoSHT(SignaltoSHT),
        .SignaltoDIV(SignaltoDIV),
        .SignaltoMUX(SignaltoMUX),
        .mulreset(mulreset)
    );
    ALU ALU (
        .dataA  (dataA),
        .dataB  (dataB),
        .Signal (SignaltoALU),
        .dataOut(ALUOut),
        .reset  (reset)
    );
    /*
    Divider Divider (
        .clk(clk),
        .dataA(dataA),
        .dataB(dataB),
        .Signal(SignaltoDIV),
        .dataOut(DivAns),
        .reset(reset)
    );
    */
    Mul mul (
        .firstart(mulreset),
        .clk(clk),
        .dataA(dataA),
        .dataB(dataB),
        .Signal(SignaltoDIV),
        .dataOut(DivAns),
        .reset(reset)
    );
    Shifter Shifter (
        .dataA  (dataA),
        .dataB  (dataB),
        .Signal (SignaltoSHT),
        .dataOut(ShifterOut),
        .reset  (reset)
    );
    HiLo HiLo (
        .clk(clk),
        .DivAns(DivAns),
        .HiOut(HiOut),
        .LoOut(LoOut),
        .reset(reset)
    );
    MUX MUX (
        .ALUOut (ALUOut),
        .HiOut  (HiOut),
        .LoOut  (LoOut),
        .Shifter(ShifterOut),
        .Signal (SignaltoMUX),
        .dataOut(dataOut)
    );

    assign Output = dataOut;


endmodule

test/tb_ALU.v
`timescale 1ns / 1ns
module tb_ALU ();
    reg clk, rst;
    reg [5:0] ctrl;
    reg [31:0] inputA, inputB, ans;
    wire [31:0] out;
    integer fp_r, fp_r_ans, eof, e;


    initial begin
        clk = 1'b1;
        forever #5 clk = ~clk;
    end

    initial begin
        inputA <= 0;
        inputB <= 0;
        ctrl   <= 0;
        $dumpfile("test.vcd");
        $dumpvars(2, alu);
        eof = 0;
        rst = 1'b1;
        #10;
        rst = 1'b0;
        fp_r = $fopen("input.txt", "r");

        fp_r_ans = $fopen("ans.txt", "r");
        $display("Start\n");
        eof = $fscanf(fp_r_ans, "%d", ans);
        while (eof != -1) begin
            e = $fscanf(fp_r, "%d%d%d", ctrl, inputA, inputB);
            $write("%d: Input: ", $time / 10);
            if (ctrl == 6'd36) $write("AND(%d)", ctrl);
            else if (ctrl == 6'd37) $write("OR(%d) ", ctrl);
            else if (ctrl == 6'd32) $write("ADD(%d) ", ctrl);
            else if (ctrl == 6'd34) $write("SUB(%d) ", ctrl);
            else if (ctrl == 6'd42) $write("SLT(%d) ", ctrl);
            else if (ctrl == 6'd2) $write("SRL(%d) ", ctrl);
            else if (ctrl == 6'd27) $write("DIVU(%d) ", ctrl);
            else if (ctrl == 6'd25) $write("MULTU(%d) ", ctrl);
            $display("%d%d", inputA, inputB);
            if (ctrl == 32'd25) begin
                #330;
                $display("%d: MUL End\n", $time / 10);
                #10;
                #10;

                $display("                   Move Hi");
                ctrl = 6'd16;
                #10;
                if (ans == out)
                    $display(
                        "%d: Correct: Your answer is:%d,\n                                 Correct answer is:%d\n",
                        $time / 10,
                        out,
                        ans
                    );
                else
                    $display(
                        "%d: Wrong Answer: Your answer is:%d,\n                                             Correct answer is:%d\n",
                        $time / 10,
                        out,
                        ans
                    );
                $display("                   Move Lo");
                ctrl = 6'd18;
                eof  = $fscanf(fp_r_ans, "%d", ans);
                #10;
                if (ans == out)
                    $display(
                        "%d: Correct: Your answer is:%d,\n                                 Correct answer is:%d\n",
                        $time / 10,
                        out,
                        ans
                    );
                else
                    $display(
                        "%d: Wrong Answer: Your answer is:%d,\n                                             Correct answer is:%d\n",
                        $time / 10,
                        out,
                        ans
                    );
            end else begin
                #10;
                if (ans == out)
                    $display(
                        "%d: Correct: Your answer is:%d,\n                                 Correct answer is:%d\n",
                        $time / 10,
                        out,
                        ans
                    );
                else
                    $display(
                        "%d: Wrong Answer: Your answer is:%d,\n                                             Correct answer is:%d\n",
                        $time / 10,
                        out,
                        ans
                    );
            end
            eof = $fscanf(fp_r_ans, "%d", ans);
        end
        $fclose(fp_r);
        $fclose(fp_r_ans);
        $display("Simulation End\n");
        $finish;
        $stop();
    end

    TotalALU alu (
        .clk(clk),
        .reset(rst),
        .dataA(inputA),
        .dataB(inputB),
        .Signal(ctrl),
        .Output(out)
    );

endmodule

/*
	AND  : 36
	OR   : 37
	ADD  : 32
	SUB  : 34
	SLT  : 42
	SRL  : 02
	DIVU : 27
*/

test/test.vcd
$date
	Thu Apr 27 21:46:16 2023
$end
$version
	Icarus Verilog
$end
$timescale
	1ns
$end
$scope module tb_ALU $end
$scope module alu $end
$var wire 32 ! Output [31:0] $end
$var wire 6 " Signal [5:0] $end
$var wire 1 # clk $end
$var wire 32 $ dataA [31:0] $end
$var wire 32 % dataB [31:0] $end
$var wire 1 & reset $end
$var wire 1 ' mulreset $end
$var wire 32 ( dataOut [31:0] $end
$var wire 6 ) SignaltoSHT [5:0] $end
$var wire 6 * SignaltoMUX [5:0] $end
$var wire 6 + SignaltoDIV [5:0] $end
$var wire 6 , SignaltoALU [5:0] $end
$var wire 32 - ShifterOut [31:0] $end
$var wire 32 . LoOut [31:0] $end
$var wire 32 / HiOut [31:0] $end
$var wire 64 0 DivAns [63:0] $end
$var wire 32 1 ALUOut [31:0] $end
$var parameter 6 2 ADD $end
$var parameter 6 3 AND $end
$var parameter 6 4 DIVU $end
$var parameter 6 5 MFHI $end
$var parameter 6 6 MFLO $end
$var parameter 6 7 OR $end
$var parameter 6 8 SLT $end
$var parameter 6 9 SRL $end
$var parameter 6 : SUB $end
$scope module ALU $end
$var wire 32 ; a [31:0] $end
$var wire 32 < dataA [31:0] $end
$var wire 32 = dataB [31:0] $end
$var wire 32 > dataOut [31:0] $end
$var wire 1 ? issub $end
$var wire 1 & reset $end
$var wire 32 @ wireor [31:0] $end
$var wire 32 A wireand [31:0] $end
$var wire 32 B sum [31:0] $end
$var wire 32 C sltsignal [31:0] $end
$var wire 2 D select [1:0] $end
$var wire 1 E isslt $end
$var wire 1 F isor $end
$var wire 1 G isand $end
$var wire 1 H isadd $end
$var wire 33 I carry [32:0] $end
$var wire 32 J b [31:0] $end
$var wire 32 K ans [31:0] $end
$var wire 6 L Signal [5:0] $end
$var parameter 6 M ADD $end
$var parameter 6 N AND $end
$var parameter 6 O OR $end
$var parameter 6 P SLT $end
$var parameter 6 Q SUB $end
$upscope $end
$scope module ALUControl $end
$var wire 6 R Signal [5:0] $end
$var wire 6 S SignaltoALU [5:0] $end
$var wire 6 T SignaltoDIV [5:0] $end
$var wire 6 U SignaltoMUX [5:0] $end
$var wire 6 V SignaltoSHT [5:0] $end
$var wire 1 # clk $end
$var parameter 6 W ADD $end
$var parameter 6 X AND $end
$var parameter 6 Y MFHI $end
$var parameter 6 Z MFLO $end
$var parameter 6 [ MULTU $end
$var parameter 6 \ OR $end
$var parameter 6 ] SLT $end
$var parameter 6 ^ SRL $end
$var parameter 6 _ SUB $end
$var reg 7 ` counter [6:0] $end
$var reg 1 ' mulreset $end
$var reg 6 a temp [5:0] $end
$upscope $end
$scope module HiLo $end
$var wire 1 # clk $end
$var wire 1 & reset $end
$var wire 32 b LoOut [31:0] $end
$var wire 32 c HiOut [31:0] $end
$var wire 64 d DivAns [63:0] $end
$var reg 64 e HiLo [63:0] $end
$upscope $end
$scope module MUX $end
$var wire 32 f ALUOut [31:0] $end
$var wire 32 g HiOut [31:0] $end
$var wire 32 h LoOut [31:0] $end
$var wire 6 i Signal [5:0] $end
$var wire 1 j alu $end
$var wire 32 k dataOut [31:0] $end
$var wire 32 l temp [31:0] $end
$var wire 1 m shif $end
$var wire 1 n lo $end
$var wire 1 o hi $end
$var wire 32 p Shifter [31:0] $end
$var parameter 6 q ADD $end
$var parameter 6 r AND $end
$var parameter 6 s DIVU $end
$var parameter 6 t MFHI $end
$var parameter 6 u MFLO $end
$var parameter 6 v OR $end
$var parameter 6 w SLT $end
$var parameter 6 x SRL $end
$var parameter 6 y SUB $end
$upscope $end
$scope module Shifter $end
$var wire 6 z Signal [5:0] $end
$var wire 32 { dataA [31:0] $end
$var wire 32 | dataB [31:0] $end
$var wire 1 & reset $end
$var wire 192 } temp [191:0] $end
$var wire 32 ~ dataOut [31:0] $end
$upscope $end
$scope module mul $end
$var wire 6 !" Signal [5:0] $end
$var wire 1 # clk $end
$var wire 32 "" dataA [31:0] $end
$var wire 32 #" dataB [31:0] $end
$var wire 64 $" dataOut [63:0] $end
$var wire 1 ' firstart $end
$var wire 1 & reset $end
$var wire 32 %" lo [31:0] $end
$var wire 32 &" hi [31:0] $end
$var reg 64 '" mcnd [63:0] $end
$var reg 32 (" mpr [31:0] $end
$var reg 64 )" temp [63:0] $end
$upscope $end
$upscope $end
$upscope $end
$enddefinitions $end
$comment Show the parameter values. $end
$dumpall
b100010 y
b10 x
b101010 w
b100101 v
b10010 u
b10000 t
b11011 s
b100100 r
b100000 q
b100010 _
b10 ^
b101010 ]
b100101 \
b11001 [
b10010 Z
b10000 Y
b100100 X
b100000 W
b100010 Q
b101010 P
b100101 O
b100100 N
b100000 M
b100010 :
b10 9
b101010 8
b100101 7
b10010 6
b10000 5
b11011 4
b100100 3
b100000 2
$end
#0
$dumpvars
bx )"
bx ("
bx '"
bx &"
bx %"
bx $"
b0 #"
b0 ""
bx !"
b0 ~
b0 }
b0 |
b0 {
bx z
b0 p
xo
xn
xm
bx l
bx k
xj
bx i
b0 h
b0 g
bx f
b0 e
bx d
b0 c
b0 b
bx a
bx `
bx V
bx U
bx T
bx S
b0 R
bx L
bx K
bx J
bx I
xH
xG
xF
xE
bx D
b0x C
bx B
b0 A
bx @
x?
bx >
b0 =
b0 <
b0 ;
bx 1
bx 0
b0 /
b0 .
b0 -
bx ,
bx +
bx *
bx )
bx (
0'
1&
b0 %
b0 $
1#
b0 "
bx !
$end
#5
b0xxxxxxxxxxxxxxxxxxxxxxxxxxxxxxx ("
bx0 '"
0#
#10
b1000 !
b1000 (
b1000 k
b1000 l
b0 C
b1000 1
b1000 >
b1000 f
b1000 K
b10110 B
1j
b10 D
b1010 J
b10000 I
0?
b1000 A
b1110 @
bx /
bx c
bx g
bx .
bx b
bx h
0o
0n
0m
b100100 *
b100100 U
b100100 i
b100100 +
b100100 T
b100100 !"
b100100 )
b100100 V
b100100 z
0E
1G
0F
0H
b100100 ,
b100100 L
b100100 S
b100100 a
bx e
1#
b1010 %
b1010 =
b1010 |
b1010 #"
b1100 ;
b11000000000000000000000000000000110000000000000000000000000000110000000000000000000000000000001100 }
b1100 $
b1100 <
b1100 {
b1100 ""
b100100 "
b100100 R
0&
#15
b0xxxxxxxxxxxxxxxxxxxxxxxxxxxxxx ("
bx00 '"
0#
#20
b1110 !
b1110 (
b1110 k
b1110 l
b1110 1
b1110 >
b1110 f
b1110 K
b1 D
b100101 *
b100101 U
b100101 i
b100101 +
b100101 T
b100101 !"
b100101 )
b100101 V
b100101 z
0G
1F
b100101 ,
b100101 L
b100101 S
b100101 a
1#
b100101 "
b100101 R
#25
b0xxxxxxxxxxxxxxxxxxxxxxxxxxxxx ("
bx000 '"
0#
#30
b10110 !
b10110 (
b10110 k
b10110 l
b10110 1
b10110 >
b10110 f
b10110 K
b0 D
b100000 *
b100000 U
b100000 i
b100000 +
b100000 T
b100000 !"
b100000 )
b100000 V
b100000 z
0F
1H
b100000 ,
b100000 L
b100000 S
b100000 a
1#
b100000 "
b100000 R
#35
b0xxxxxxxxxxxxxxxxxxxxxxxxxxxx ("
bx0000 '"
0#
#40
b10 !
b10 (
b10 k
b10 l
b0 C
b10 1
b10 >
b10 f
b10 K
b100 A
b11111111111111111111111111111101 @
b0 D
b10 B
b11111111111111111111111111110101 J
b111111111111111111111111111111011 I
1?
b100010 *
b100010 U
b100010 i
b100010 +
b100010 T
b100010 !"
b100010 )
b100010 V
b100010 z
0H
b100010 ,
b100010 L
b100010 S
b100010 a
1#
b100010 "
b100010 R
#45
b0xxxxxxxxxxxxxxxxxxxxxxxxxxx ("
bx00000 '"
0#
#50
b0 !
b0 (
b0 k
b0 l
b0 1
b0 >
b0 f
b0 K
b1010 B
b11 -
b11 p
b11 ~
b1100 A
b11 D
b11111111111111111111111111111101 J
b110000000000000000000000000000001100000000000000000000000000000011000000000000000000000000000000110000000000000000000000000000110000000000000000000000000000001100 }
b101010 *
b101010 U
b101010 i
b101010 +
b101010 T
b101010 !"
b101010 )
b101010 V
b101010 z
1E
b101010 ,
b101010 L
b101010 S
b101010 a
1#
b10 %
b10 =
b10 |
b10 #"
b101010 "
b101010 R
#55
b0xxxxxxxxxxxxxxxxxxxxxxxxxx ("
bx000000 '"
0#
#60
b1 !
b1 (
b1 k
b1 l
b1 1
b1 >
b1 f
b1 K
b1 C
b11001111 I
b0 -
b0 p
b0 ~
b11111111111111111111111101110111 @
b11111111111111111111111110011100 B
b11111111111111111111111100110111 J
b100100 A
1#
b11001000 %
b11001000 =
b11001000 |
b11001000 #"
b1100100 ;
b1100100000000000000000000000000011001000000000000000000000000000110010000000000000000000000000001100100 }
b1100100 $
b1100100 <
b1100100 {
b1100100 ""
#65
b0xxxxxxxxxxxxxxxxxxxxxxxxx ("
bx0000000 '"
0#
#70
b0 C
b11 !
b11 (
b11 k
b11 l
b0 1
b0 >
b0 f
b0 K
b11 -
b11 p
b11 ~
b10 D
b1110 B
0j
b0 I
0?
b10 J
b0 A
b1110 @
1m
b10 *
b10 U
b10 i
b10 +
b10 T
b10 !"
b10 )
b10 V
b10 z
0E
b10 ,
b10 L
b10 S
b10 a
1#
b10 %
b10 =
b10 |
b10 #"
b1100 ;
b110000000000000000000000000000001100000000000000000000000000000011000000000000000000000000000000110000000000000000000000000000110000000000000000000000000000001100 }
b1100 $
b1100 <
b1100 {
b1100 ""
b10 "
b10 R
#75
b0xxxxxxxxxxxxxxxxxxxxxxxx ("
bx00000000 '"
0#
#80
b10 !
b10 (
b10 k
b10 l
b10 -
b10 p
b10 ~
b10000110 B
b110 J
b10000110 @
1#
b110 %
b110 =
b110 |
b110 #"
b10000000 ;
b100000000000000000000000000000001000000000000000000000000000000010000000000000000000000000001000000000000000000000000000001000000000000000000000000000000010000000 }
b10000000 $
b10000000 <
b10000000 {
b10000000 ""
#85
b0xxxxxxxxxxxxxxxxxxxxxxx ("
bx000000000 '"
0#
#90
b1 C
b111111111111111111111111111111 !
b111111111111111111111111111111 (
b111111111111111111111111111111 k
b111111111111111111111111111111 l
b111111111111111111111111111111 -
b111111111111111111111111111111 p
b111111111111111111111111111111 ~
b11111111111111111111111111111110 I
b1 1
b1 >
b1 f
b1 K
b10000000000000000000000000000000 B
b1 J
b1 A
b1111111111111111111111111111111 @
1#
b1 %
b1 =
b1 |
b1 #"
b1111111111111111111111111111111 ;
b1111111111111111111111111111110011111111111111111111111111111100111111111111111111111111111111001111111111111111111111111111110011111111111111111111111111111101111111111111111111111111111111 }
b1111111111111111111111111111111 $
b1111111111111111111111111111111 <
b1111111111111111111111111111111 {
b1111111111111111111111111111111 ""
#95
b0xxxxxxxxxxxxxxxxxxxxxx ("
bx0000000000 '"
0#
#100
b11111111111111111111111111 !
b11111111111111111111111111 (
b11111111111111111111111111 k
b11111111111111111111111111 l
b11111111111111111111111111 -
b11111111111111111111111111 p
b11111111111111111111111111 ~
b101 1
b101 >
b101 f
b101 K
b10000000000000000000000000000100 B
b101 A
b101 J
b111111111111111111111111110000001111111111111111111111111100000011111111111111111111111111001111111111111111111111111111110011111111111111111111111111111101111111111111111111111111111111 }
1#
b101 %
b101 =
b101 |
b101 #"
#105
b0xxxxxxxxxxxxxxxxxxxxx ("
bx00000000000 '"
0#
#110
b1111111111111111111111111 !
b1111111111111111111111111 (
b1111111111111111111111111 k
b1111111111111111111111111 l
b1111111111111111111111111 -
b1111111111111111111111111 p
b1111111111111111111111111 ~
b11111111111111111111111111111100 I
b110 1
b110 >
b110 f
b110 K
b10000000000000000000000000000101 B
b110 A
b110 J
b11111111111111111111111110000000111111111111111111111111100000001111111111111111111111111000111111111111111111111111111110111111111111111111111111111111101111111111111111111111111111111 }
1#
b110 %
b110 =
b110 |
b110 #"
#115
b0xxxxxxxxxxxxxxxxxxxx ("
bx000000000000 '"
0#
#120
b0 &"
b0 %"
b11110 '"
b10001 ("
b0 0
b0 d
b0 $"
b0 )"
1'
b0 C
b10000 1
b10000 >
b10000 f
b10000 K
b10000 A
b100000 I
b0 !
b0 (
b0 k
b0 l
b0 -
b0 p
b0 ~
b101111 B
b10001 J
b11111 @
0m
b11001 *
b11001 U
b11001 i
b11001 +
b11001 T
b11001 !"
b11001 )
b11001 V
b11001 z
b11001 ,
b11001 L
b11001 S
b11001 a
b1 `
1#
b10001 %
b10001 =
b10001 |
b10001 #"
b11110 ;
b111100000000000000000000000000001111000000000000000000000000000011110000000000000000000000000000111100000000000000000000000000011110 }
b11110 $
b11110 <
b11110 {
b11110 ""
b11001 "
b11001 R
#125
b1000 ("
b111100 '"
b11110 %"
b11110 0
b11110 d
b11110 $"
b11110 )"
0#
#130
0'
b0 /
b0 c
b0 g
b11110 .
b11110 b
b11110 h
b10 `
b11110 e
1#
#135
b100 ("
b1111000 '"
0#
#140
b11 `
1#
#145
b10 ("
b11110000 '"
0#
#150
b100 `
1#
#155
b1 ("
b111100000 '"
0#
#160
b101 `
1#
#165
b0 ("
b1111000000 '"
b111111110 %"
b111111110 0
b111111110 d
b111111110 $"
b111111110 )"
0#
#170
b111111110 .
b111111110 b
b111111110 h
b110 `
b111111110 e
1#
#175
b11110000000 '"
0#
#180
b111 `
1#
#185
b111100000000 '"
0#
#190
b1000 `
1#
#195
b1111000000000 '"
0#
#200
b1001 `
1#
#205
b11110000000000 '"
0#
#210
b1010 `
1#
#215
b111100000000000 '"
0#
#220
b1011 `
1#
#225
b1111000000000000 '"
0#
#230
b1100 `
1#
#235
b11110000000000000 '"
0#
#240
b1101 `
1#
#245
b111100000000000000 '"
0#
#250
b1110 `
1#
#255
b1111000000000000000 '"
0#
#260
b1111 `
1#
#265
b11110000000000000000 '"
0#
#270
b10000 `
1#
#275
b111100000000000000000 '"
0#
#280
b10001 `
1#
#285
b1111000000000000000000 '"
0#
#290
b10010 `
1#
#295
b11110000000000000000000 '"
0#
#300
b10011 `
1#
#305
b111100000000000000000000 '"
0#
#310
b10100 `
1#
#315
b1111000000000000000000000 '"
0#
#320
b10101 `
1#
#325
b11110000000000000000000000 '"
0#
#330
b10110 `
1#
#335
b111100000000000000000000000 '"
0#
#340
b10111 `
1#
#345
b1111000000000000000000000000 '"
0#
#350
b11000 `
1#
#355
b11110000000000000000000000000 '"
0#
#360
b11001 `
1#
#365
b111100000000000000000000000000 '"
0#
#370
b11010 `
1#
#375
b1111000000000000000000000000000 '"
0#
#380
b11011 `
1#
#385
b11110000000000000000000000000000 '"
0#
#390
b11100 `
1#
#395
b111100000000000000000000000000000 '"
0#
#400
b11101 `
1#
#405
b1111000000000000000000000000000000 '"
0#
#410
b11110 `
1#
#415
b11110000000000000000000000000000000 '"
0#
#420
b11111 `
1#
#425
b111100000000000000000000000000000000 '"
0#
#430
b111111 *
b111111 U
b111111 i
b111111 +
b111111 T
b111111 !"
b111111 )
b111111 V
b111111 z
b111111 ,
b111111 L
b111111 S
b111111 a
b0 `
1#
#435
b1111000000000000000000000000000000000 '"
0#
#440
b1 `
b11001 *
b11001 U
b11001 i
b11001 +
b11001 T
b11001 !"
b11001 )
b11001 V
b11001 z
b11001 ,
b11001 L
b11001 S
b11001 a
1#
#445
b11110000000000000000000000000000000000 '"
0#
#450
b10 `
1#
#455
b111100000000000000000000000000000000000 '"
0#
#460
b11 `
1#
#465
b1111000000000000000000000000000000000000 '"
0#
#470
1o
b10000 *
b10000 U
b10000 i
b10000 +
b10000 T
b10000 !"
b10000 )
b10000 V
b10000 z
b10000 ,
b10000 L
b10000 S
b10000 a
1#
b10000 "
b10000 R
#475
b11110000000000000000000000000000000000000 '"
0#
#480
b111111110 !
b111111110 (
b111111110 k
b111111110 l
0o
1n
b10010 *
b10010 U
b10010 i
b10010 +
b10010 T
b10010 !"
b10010 )
b10010 V
b10010 z
b10010 ,
b10010 L
b10010 S
b10010 a
1#
b10010 "
b10010 R
#485
b111100000000000000000000000000000000000000 '"
0#
#490
b0 %"
b111011100110101100100111111111 '"
b111011100110101100100111111111 ("
b0 0
b0 d
b0 $"
b0 )"
1'
b0 !
b0 (
b0 k
b0 l
b111011100110101100100111111111 1
b111011100110101100100111111111 >
b111011100110101100100111111111 f
b111011100110101100100111111111 K
b1110111001101011001001111111110 I
b1110111001101011001001111111110 B
b111011100110101100100111111111 J
b111011100110101100100111111111 A
b111011100110101100100111111111 @
0n
b11001 *
b11001 U
b11001 i
b11001 +
b11001 T
b11001 !"
b11001 )
b11001 V
b11001 z
b11001 ,
b11001 L
b11001 S
b11001 a
b1 `
1#
b111011100110101100100111111111 %
b111011100110101100100111111111 =
b111011100110101100100111111111 |
b111011100110101100100111111111 #"
b111011100110101100100111111111 ;
b11101110011010100000000011101110011010110010011000001110111001101011001001111110001110111001101011001001111111100111011100110101100100111111111 }
b111011100110101100100111111111 $
b111011100110101100100111111111 <
b111011100110101100100111111111 {
b111011100110101100100111111111 ""
b11001 "
b11001 R
#495
b11101110011010110010011111111 ("
b1110111001101011001001111111110 '"
b111011100110101100100111111111 %"
b111011100110101100100111111111 0
b111011100110101100100111111111 d
b111011100110101100100111111111 $"
b111011100110101100100111111111 )"
0#
